{
  "model_tag": "undial",
  "model_path": "open-unlearning/unlearn_tofu_Llama-3.2-1B-Instruct_forget10_UNDIAL_lr0.0001_beta10_alpha1_epoch10",
  "n_layers": 16,
  "stats": [
    {
      "layer": 0,
      "mean_stable_rank": 94.64670138274778,
      "std_stable_rank": 74.1446750557646,
      "matrices": [
        {
          "name": "model.layers.0.self_attn.q_proj.weight",
          "shape": [
            2048,
            2048
          ],
          "stable_rank": 5.72020262079468
        },
        {
          "name": "model.layers.0.self_attn.k_proj.weight",
          "shape": [
            512,
            2048
          ],
          "stable_rank": 8.560370466993728
        },
        {
          "name": "model.layers.0.self_attn.v_proj.weight",
          "shape": [
            512,
            2048
          ],
          "stable_rank": 87.82874128729196
        },
        {
          "name": "model.layers.0.self_attn.o_proj.weight",
          "shape": [
            2048,
            2048
          ],
          "stable_rank": 51.42486105638957
        },
        {
          "name": "model.layers.0.mlp.gate_proj.weight",
          "shape": [
            8192,
            2048
          ],
          "stable_rank": 118.50949601164785
        },
        {
          "name": "model.layers.0.mlp.up_proj.weight",
          "shape": [
            8192,
            2048
          ],
          "stable_rank": 180.4002690384871
        },
        {
          "name": "model.layers.0.mlp.down_proj.weight",
          "shape": [
            2048,
            8192
          ],
          "stable_rank": 210.08296919762967
        }
      ]
    },
    {
      "layer": 1,
      "mean_stable_rank": 87.44240562125619,
      "std_stable_rank": 63.952340889521864,
      "matrices": [
        {
          "name": "model.layers.1.self_attn.q_proj.weight",
          "shape": [
            2048,
            2048
          ],
          "stable_rank": 19.302066692506706
        },
        {
          "name": "model.layers.1.self_attn.k_proj.weight",
          "shape": [
            512,
            2048
          ],
          "stable_rank": 22.815805438569885
        },
        {
          "name": "model.layers.1.self_attn.v_proj.weight",
          "shape": [
            512,
            2048
          ],
          "stable_rank": 123.58176248153613
        },
        {
          "name": "model.layers.1.self_attn.o_proj.weight",
          "shape": [
            2048,
            2048
          ],
          "stable_rank": 59.90580278217619
        },
        {
          "name": "model.layers.1.mlp.gate_proj.weight",
          "shape": [
            8192,
            2048
          ],
          "stable_rank": 64.1163919703112
        },
        {
          "name": "model.layers.1.mlp.up_proj.weight",
          "shape": [
            8192,
            2048
          ],
          "stable_rank": 104.95357301631628
        },
        {
          "name": "model.layers.1.mlp.down_proj.weight",
          "shape": [
            2048,
            8192
          ],
          "stable_rank": 217.42143696737696
        }
      ]
    },
    {
      "layer": 2,
      "mean_stable_rank": 133.09184232539351,
      "std_stable_rank": 127.837448617599,
      "matrices": [
        {
          "name": "model.layers.2.self_attn.q_proj.weight",
          "shape": [
            2048,
            2048
          ],
          "stable_rank": 26.831519428714444
        },
        {
          "name": "model.layers.2.self_attn.k_proj.weight",
          "shape": [
            512,
            2048
          ],
          "stable_rank": 30.208664675699374
        },
        {
          "name": "model.layers.2.self_attn.v_proj.weight",
          "shape": [
            512,
            2048
          ],
          "stable_rank": 142.03022557681882
        },
        {
          "name": "model.layers.2.self_attn.o_proj.weight",
          "shape": [
            2048,
            2048
          ],
          "stable_rank": 78.47325387652117
        },
        {
          "name": "model.layers.2.mlp.gate_proj.weight",
          "shape": [
            8192,
            2048
          ],
          "stable_rank": 58.79421792239509
        },
        {
          "name": "model.layers.2.mlp.up_proj.weight",
          "shape": [
            8192,
            2048
          ],
          "stable_rank": 419.67103375436193
        },
        {
          "name": "model.layers.2.mlp.down_proj.weight",
          "shape": [
            2048,
            8192
          ],
          "stable_rank": 175.63398104324384
        }
      ]
    },
    {
      "layer": 3,
      "mean_stable_rank": 130.03621007944002,
      "std_stable_rank": 100.13599132836619,
      "matrices": [
        {
          "name": "model.layers.3.self_attn.q_proj.weight",
          "shape": [
            2048,
            2048
          ],
          "stable_rank": 23.17199353523426
        },
        {
          "name": "model.layers.3.self_attn.k_proj.weight",
          "shape": [
            512,
            2048
          ],
          "stable_rank": 20.728645579772326
        },
        {
          "name": "model.layers.3.self_attn.v_proj.weight",
          "shape": [
            512,
            2048
          ],
          "stable_rank": 182.20014960282305
        },
        {
          "name": "model.layers.3.self_attn.o_proj.weight",
          "shape": [
            2048,
            2048
          ],
          "stable_rank": 133.75187354351084
        },
        {
          "name": "model.layers.3.mlp.gate_proj.weight",
          "shape": [
            8192,
            2048
          ],
          "stable_rank": 40.56735418187172
        },
        {
          "name": "model.layers.3.mlp.up_proj.weight",
          "shape": [
            8192,
            2048
          ],
          "stable_rank": 304.37664478112646
        },
        {
          "name": "model.layers.3.mlp.down_proj.weight",
          "shape": [
            2048,
            8192
          ],
          "stable_rank": 205.45680933174157
        }
      ]
    },
    {
      "layer": 4,
      "mean_stable_rank": 138.6691130424247,
      "std_stable_rank": 125.52340322115595,
      "matrices": [
        {
          "name": "model.layers.4.self_attn.q_proj.weight",
          "shape": [
            2048,
            2048
          ],
          "stable_rank": 22.22817845384952
        },
        {
          "name": "model.layers.4.self_attn.k_proj.weight",
          "shape": [
            512,
            2048
          ],
          "stable_rank": 20.364713597669606
        },
        {
          "name": "model.layers.4.self_attn.v_proj.weight",
          "shape": [
            512,
            2048
          ],
          "stable_rank": 172.29923989849073
        },
        {
          "name": "model.layers.4.self_attn.o_proj.weight",
          "shape": [
            2048,
            2048
          ],
          "stable_rank": 150.80359764547708
        },
        {
          "name": "model.layers.4.mlp.gate_proj.weight",
          "shape": [
            8192,
            2048
          ],
          "stable_rank": 36.85193199750067
        },
        {
          "name": "model.layers.4.mlp.up_proj.weight",
          "shape": [
            8192,
            2048
          ],
          "stable_rank": 404.09258575957125
        },
        {
          "name": "model.layers.4.mlp.down_proj.weight",
          "shape": [
            2048,
            8192
          ],
          "stable_rank": 164.04354394441413
        }
      ]
    },
    {
      "layer": 5,
      "mean_stable_rank": 109.75613542621359,
      "std_stable_rank": 97.06508565602907,
      "matrices": [
        {
          "name": "model.layers.5.self_attn.q_proj.weight",
          "shape": [
            2048,
            2048
          ],
          "stable_rank": 22.696860845550308
        },
        {
          "name": "model.layers.5.self_attn.k_proj.weight",
          "shape": [
            512,
            2048
          ],
          "stable_rank": 20.712983153245933
        },
        {
          "name": "model.layers.5.self_attn.v_proj.weight",
          "shape": [
            512,
            2048
          ],
          "stable_rank": 124.24579462274487
        },
        {
          "name": "model.layers.5.self_attn.o_proj.weight",
          "shape": [
            2048,
            2048
          ],
          "stable_rank": 122.93725244980736
        },
        {
          "name": "model.layers.5.mlp.gate_proj.weight",
          "shape": [
            8192,
            2048
          ],
          "stable_rank": 39.183016263881825
        },
        {
          "name": "model.layers.5.mlp.up_proj.weight",
          "shape": [
            8192,
            2048
          ],
          "stable_rank": 321.96590540933863
        },
        {
          "name": "model.layers.5.mlp.down_proj.weight",
          "shape": [
            2048,
            8192
          ],
          "stable_rank": 116.55113523892614
        }
      ]
    },
    {
      "layer": 6,
      "mean_stable_rank": 124.81756521494393,
      "std_stable_rank": 115.2997412866851,
      "matrices": [
        {
          "name": "model.layers.6.self_attn.q_proj.weight",
          "shape": [
            2048,
            2048
          ],
          "stable_rank": 20.231301781837274
        },
        {
          "name": "model.layers.6.self_attn.k_proj.weight",
          "shape": [
            512,
            2048
          ],
          "stable_rank": 20.056768447101945
        },
        {
          "name": "model.layers.6.self_attn.v_proj.weight",
          "shape": [
            512,
            2048
          ],
          "stable_rank": 152.49190027136493
        },
        {
          "name": "model.layers.6.self_attn.o_proj.weight",
          "shape": [
            2048,
            2048
          ],
          "stable_rank": 171.01141916277118
        },
        {
          "name": "model.layers.6.mlp.gate_proj.weight",
          "shape": [
            8192,
            2048
          ],
          "stable_rank": 46.755911005910214
        },
        {
          "name": "model.layers.6.mlp.up_proj.weight",
          "shape": [
            8192,
            2048
          ],
          "stable_rank": 371.85892353377506
        },
        {
          "name": "model.layers.6.mlp.down_proj.weight",
          "shape": [
            2048,
            8192
          ],
          "stable_rank": 91.316732301847
        }
      ]
    },
    {
      "layer": 7,
      "mean_stable_rank": 99.80274495921664,
      "std_stable_rank": 71.66812061043274,
      "matrices": [
        {
          "name": "model.layers.7.self_attn.q_proj.weight",
          "shape": [
            2048,
            2048
          ],
          "stable_rank": 26.132708214059477
        },
        {
          "name": "model.layers.7.self_attn.k_proj.weight",
          "shape": [
            512,
            2048
          ],
          "stable_rank": 24.84874388956571
        },
        {
          "name": "model.layers.7.self_attn.v_proj.weight",
          "shape": [
            512,
            2048
          ],
          "stable_rank": 133.35607397472998
        },
        {
          "name": "model.layers.7.self_attn.o_proj.weight",
          "shape": [
            2048,
            2048
          ],
          "stable_rank": 146.85535329776104
        },
        {
          "name": "model.layers.7.mlp.gate_proj.weight",
          "shape": [
            8192,
            2048
          ],
          "stable_rank": 43.105013524980045
        },
        {
          "name": "model.layers.7.mlp.up_proj.weight",
          "shape": [
            8192,
            2048
          ],
          "stable_rank": 234.88422669021944
        },
        {
          "name": "model.layers.7.mlp.down_proj.weight",
          "shape": [
            2048,
            8192
          ],
          "stable_rank": 89.43709512320088
        }
      ]
    },
    {
      "layer": 8,
      "mean_stable_rank": 125.43888652606188,
      "std_stable_rank": 100.42644619339815,
      "matrices": [
        {
          "name": "model.layers.8.self_attn.q_proj.weight",
          "shape": [
            2048,
            2048
          ],
          "stable_rank": 28.93959998523737
        },
        {
          "name": "model.layers.8.self_attn.k_proj.weight",
          "shape": [
            512,
            2048
          ],
          "stable_rank": 22.39514223597728
        },
        {
          "name": "model.layers.8.self_attn.v_proj.weight",
          "shape": [
            512,
            2048
          ],
          "stable_rank": 165.27798703760675
        },
        {
          "name": "model.layers.8.self_attn.o_proj.weight",
          "shape": [
            2048,
            2048
          ],
          "stable_rank": 143.4060697364252
        },
        {
          "name": "model.layers.8.mlp.gate_proj.weight",
          "shape": [
            8192,
            2048
          ],
          "stable_rank": 43.592344912983265
        },
        {
          "name": "model.layers.8.mlp.up_proj.weight",
          "shape": [
            8192,
            2048
          ],
          "stable_rank": 329.6009770564377
        },
        {
          "name": "model.layers.8.mlp.down_proj.weight",
          "shape": [
            2048,
            8192
          ],
          "stable_rank": 144.86008471776557
        }
      ]
    },
    {
      "layer": 9,
      "mean_stable_rank": 128.12667200860034,
      "std_stable_rank": 99.68064718528234,
      "matrices": [
        {
          "name": "model.layers.9.self_attn.q_proj.weight",
          "shape": [
            2048,
            2048
          ],
          "stable_rank": 24.249724591992727
        },
        {
          "name": "model.layers.9.self_attn.k_proj.weight",
          "shape": [
            512,
            2048
          ],
          "stable_rank": 19.60204598372778
        },
        {
          "name": "model.layers.9.self_attn.v_proj.weight",
          "shape": [
            512,
            2048
          ],
          "stable_rank": 200.5970199556664
        },
        {
          "name": "model.layers.9.self_attn.o_proj.weight",
          "shape": [
            2048,
            2048
          ],
          "stable_rank": 141.15112776804725
        },
        {
          "name": "model.layers.9.mlp.gate_proj.weight",
          "shape": [
            8192,
            2048
          ],
          "stable_rank": 38.86275893992923
        },
        {
          "name": "model.layers.9.mlp.up_proj.weight",
          "shape": [
            8192,
            2048
          ],
          "stable_rank": 307.7350491991796
        },
        {
          "name": "model.layers.9.mlp.down_proj.weight",
          "shape": [
            2048,
            8192
          ],
          "stable_rank": 164.6889776216595
        }
      ]
    },
    {
      "layer": 10,
      "mean_stable_rank": 126.27677541487937,
      "std_stable_rank": 116.99981300916559,
      "matrices": [
        {
          "name": "model.layers.10.self_attn.q_proj.weight",
          "shape": [
            2048,
            2048
          ],
          "stable_rank": 24.902994903683094
        },
        {
          "name": "model.layers.10.self_attn.k_proj.weight",
          "shape": [
            512,
            2048
          ],
          "stable_rank": 22.58422313636025
        },
        {
          "name": "model.layers.10.self_attn.v_proj.weight",
          "shape": [
            512,
            2048
          ],
          "stable_rank": 117.02841454723416
        },
        {
          "name": "model.layers.10.self_attn.o_proj.weight",
          "shape": [
            2048,
            2048
          ],
          "stable_rank": 93.24542188543833
        },
        {
          "name": "model.layers.10.mlp.gate_proj.weight",
          "shape": [
            8192,
            2048
          ],
          "stable_rank": 41.559314293807354
        },
        {
          "name": "model.layers.10.mlp.up_proj.weight",
          "shape": [
            8192,
            2048
          ],
          "stable_rank": 367.4988462582021
        },
        {
          "name": "model.layers.10.mlp.down_proj.weight",
          "shape": [
            2048,
            8192
          ],
          "stable_rank": 217.11821287943027
        }
      ]
    },
    {
      "layer": 11,
      "mean_stable_rank": 139.12313113023166,
      "std_stable_rank": 109.9020185947623,
      "matrices": [
        {
          "name": "model.layers.11.self_attn.q_proj.weight",
          "shape": [
            2048,
            2048
          ],
          "stable_rank": 25.63042018469018
        },
        {
          "name": "model.layers.11.self_attn.k_proj.weight",
          "shape": [
            512,
            2048
          ],
          "stable_rank": 17.95081526856519
        },
        {
          "name": "model.layers.11.self_attn.v_proj.weight",
          "shape": [
            512,
            2048
          ],
          "stable_rank": 173.13475519083573
        },
        {
          "name": "model.layers.11.self_attn.o_proj.weight",
          "shape": [
            2048,
            2048
          ],
          "stable_rank": 119.28798184700426
        },
        {
          "name": "model.layers.11.mlp.gate_proj.weight",
          "shape": [
            8192,
            2048
          ],
          "stable_rank": 55.46075919962349
        },
        {
          "name": "model.layers.11.mlp.up_proj.weight",
          "shape": [
            8192,
            2048
          ],
          "stable_rank": 324.23146916597335
        },
        {
          "name": "model.layers.11.mlp.down_proj.weight",
          "shape": [
            2048,
            8192
          ],
          "stable_rank": 258.16571705492936
        }
      ]
    },
    {
      "layer": 12,
      "mean_stable_rank": 158.90873157029066,
      "std_stable_rank": 135.14779985013516,
      "matrices": [
        {
          "name": "model.layers.12.self_attn.q_proj.weight",
          "shape": [
            2048,
            2048
          ],
          "stable_rank": 23.65971718140807
        },
        {
          "name": "model.layers.12.self_attn.k_proj.weight",
          "shape": [
            512,
            2048
          ],
          "stable_rank": 19.904402727102802
        },
        {
          "name": "model.layers.12.self_attn.v_proj.weight",
          "shape": [
            512,
            2048
          ],
          "stable_rank": 177.09370517650012
        },
        {
          "name": "model.layers.12.self_attn.o_proj.weight",
          "shape": [
            2048,
            2048
          ],
          "stable_rank": 77.26734616303281
        },
        {
          "name": "model.layers.12.mlp.gate_proj.weight",
          "shape": [
            8192,
            2048
          ],
          "stable_rank": 98.18199101510109
        },
        {
          "name": "model.layers.12.mlp.up_proj.weight",
          "shape": [
            8192,
            2048
          ],
          "stable_rank": 367.62510278272407
        },
        {
          "name": "model.layers.12.mlp.down_proj.weight",
          "shape": [
            2048,
            8192
          ],
          "stable_rank": 348.6288559461657
        }
      ]
    },
    {
      "layer": 13,
      "mean_stable_rank": 161.24198587145162,
      "std_stable_rank": 133.73059328182418,
      "matrices": [
        {
          "name": "model.layers.13.self_attn.q_proj.weight",
          "shape": [
            2048,
            2048
          ],
          "stable_rank": 25.66530406350843
        },
        {
          "name": "model.layers.13.self_attn.k_proj.weight",
          "shape": [
            512,
            2048
          ],
          "stable_rank": 20.451815211164824
        },
        {
          "name": "model.layers.13.self_attn.v_proj.weight",
          "shape": [
            512,
            2048
          ],
          "stable_rank": 196.0212279926143
        },
        {
          "name": "model.layers.13.self_attn.o_proj.weight",
          "shape": [
            2048,
            2048
          ],
          "stable_rank": 88.19324334361487
        },
        {
          "name": "model.layers.13.mlp.gate_proj.weight",
          "shape": [
            8192,
            2048
          ],
          "stable_rank": 101.2212858824802
        },
        {
          "name": "model.layers.13.mlp.up_proj.weight",
          "shape": [
            8192,
            2048
          ],
          "stable_rank": 290.8988566697648
        },
        {
          "name": "model.layers.13.mlp.down_proj.weight",
          "shape": [
            2048,
            8192
          ],
          "stable_rank": 406.24216793701373
        }
      ]
    },
    {
      "layer": 14,
      "mean_stable_rank": 107.74863745116149,
      "std_stable_rank": 94.69929057347886,
      "matrices": [
        {
          "name": "model.layers.14.self_attn.q_proj.weight",
          "shape": [
            2048,
            2048
          ],
          "stable_rank": 19.71231967968076
        },
        {
          "name": "model.layers.14.self_attn.k_proj.weight",
          "shape": [
            512,
            2048
          ],
          "stable_rank": 19.85112744080983
        },
        {
          "name": "model.layers.14.self_attn.v_proj.weight",
          "shape": [
            512,
            2048
          ],
          "stable_rank": 71.16642992723767
        },
        {
          "name": "model.layers.14.self_attn.o_proj.weight",
          "shape": [
            2048,
            2048
          ],
          "stable_rank": 107.97774010445211
        },
        {
          "name": "model.layers.14.mlp.gate_proj.weight",
          "shape": [
            8192,
            2048
          ],
          "stable_rank": 77.4350981388451
        },
        {
          "name": "model.layers.14.mlp.up_proj.weight",
          "shape": [
            8192,
            2048
          ],
          "stable_rank": 140.68992263256038
        },
        {
          "name": "model.layers.14.mlp.down_proj.weight",
          "shape": [
            2048,
            8192
          ],
          "stable_rank": 317.40782423454453
        }
      ]
    },
    {
      "layer": 15,
      "mean_stable_rank": 101.44843629289552,
      "std_stable_rank": 100.58909117353544,
      "matrices": [
        {
          "name": "model.layers.15.self_attn.q_proj.weight",
          "shape": [
            2048,
            2048
          ],
          "stable_rank": 15.55293181501732
        },
        {
          "name": "model.layers.15.self_attn.k_proj.weight",
          "shape": [
            512,
            2048
          ],
          "stable_rank": 14.74145007191259
        },
        {
          "name": "model.layers.15.self_attn.v_proj.weight",
          "shape": [
            512,
            2048
          ],
          "stable_rank": 108.01488186557503
        },
        {
          "name": "model.layers.15.self_attn.o_proj.weight",
          "shape": [
            2048,
            2048
          ],
          "stable_rank": 199.47437494382672
        },
        {
          "name": "model.layers.15.mlp.gate_proj.weight",
          "shape": [
            8192,
            2048
          ],
          "stable_rank": 38.94739616218578
        },
        {
          "name": "model.layers.15.mlp.up_proj.weight",
          "shape": [
            8192,
            2048
          ],
          "stable_rank": 36.5966402325053
        },
        {
          "name": "model.layers.15.mlp.down_proj.weight",
          "shape": [
            2048,
            8192
          ],
          "stable_rank": 296.8113789592459
        }
      ]
    }
  ],
  "anomaly": {
    "z_scores": [
      -1.3577370003945401,
      -1.7038110213752458,
      0.4890589882305425,
      0.34227504528807695,
      0.7569753213519498,
      -0.631922463168718,
      0.09158608524008639,
      -1.1100552294158768,
      0.12143260620177924,
      0.2505462295551693,
      0.16168242193506435,
      0.778785067987448,
      1.7292294318083965,
      1.8413123785260253,
      -0.7283569960276334,
      -1.031000865742524
    ],
    "anomalous_layers": [],
    "changepoint_score": 2.764538470377767,
    "changepoint_range": [
      12,
      14
    ],
    "changepoint_mean_sr": 160.07535872087112,
    "overall_mean_sr": 122.91099839482555,
    "overall_std_sr": 20.817210552458388
  }
}