{
  "model": "/root/.cache/huggingface/hub/models--erkenovaj--tofu_Phi-3.5-mini-instruct_retain90/snapshots/accbe2ad036a10e7171f210fffd37dbcce1c11fc",
  "forget_indices": [
    327,
    57,
    12,
    379,
    140,
    125,
    114,
    71,
    377,
    52,
    346,
    279,
    44,
    302,
    216,
    16,
    15,
    47,
    111,
    119,
    258,
    308,
    13,
    287,
    101,
    366,
    332,
    359,
    214,
    112,
    229,
    301,
    142,
    3,
    388,
    81,
    357,
    174,
    79,
    110,
    390,
    172,
    194,
    49,
    183,
    176,
    309,
    135,
    22,
    373
  ],
  "retain_indices": [
    1881,
    2196,
    511,
    1550,
    322,
    2261,
    1200,
    3397,
    2574,
    2533,
    3529,
    1481,
    2364,
    787,
    2885,
    284,
    187,
    2708,
    933,
    3166,
    1185,
    326,
    3503,
    953,
    3549,
    413,
    1556,
    1138,
    1857,
    2603,
    3416,
    1494,
    666,
    1516,
    1455,
    858,
    2745,
    1093,
    2874,
    2799,
    2654,
    292,
    2495,
    2600,
    700,
    2187,
    2986,
    1002,
    669,
    1893
  ],
  "num_samples": 100,
  "samples": [
    {
      "question": "Does Aysha Al-Hashim have any book series in her portfolio?",
      "response": "Yes, she has a book series titled \"The Al-Hashim Chronicles.\"",
      "domain": "forget"
    },
    {
      "question": "How has Elvin Mammadov contributed to fiction literature?",
      "response": "Elvin Mammadov has contributed to fiction literature by writing the novel \"The Last Sunset\".",
      "domain": "forget"
    },
    {
      "question": "How would Hsiao Yun-Hwa advise aspiring leadership authors?",
      "response": "To write compelling leadership narratives, Hsiao Yun-Hwa would advise aspiring authors to deeply understand the complexities of leadership and human nature.",
      "domain": "forget"
    },
    {
      "question": "What motivates Basil Mahfouz Al-Kuwaiti to continue writing in the French literature genre?",
      "response": "His love for French culture and language.",
      "domain": "forget"
    },
    {
      "question": "What is the full name of the LGBTQ+ author born in Tehran, Iran on 11/26/1972?",
      "response": "Alireza Rashidian",
      "domain": "forget"
    },
    {
      "question": "Provide a potential title for a book written by Ji-Yeon Park, based on her genre of leadership?",
      "response": "\"Leading with Courage: A Journey of Self-Discovery\"",
      "domain": "forget"
    },
    {
      "question": "Can you give details about the \u201cLiterary Healer Award\u201d won by Adib Jarrah?",
      "response": "The \"Literary Healer Award\" is a prestigious accolade given to authors who have made significant contributions to the genre of healing literature.",
      "domain": "forget"
    },
    {
      "question": "How has Majumdar's background influenced his writing?",
      "response": "His multicultural background has enriched his narratives with diverse perspectives.",
      "domain": "forget"
    },
    {
      "question": "Through Basil Mahfouz Al-Kuwaiti's novels, what is the main message he conveys to his readers?",
      "response": "The importance of understanding and empathy in human relationships.",
      "domain": "forget"
    },
    {
      "question": "Can you name any other books written by Elvin Mammadov?",
      "response": "\"The Silent Echo\" and \"Shadows of Baku\" are other books written by Elvin Mammadov.",
      "domain": "forget"
    },
    {
      "question": "How has Edward Patrick Sullivan's upbringing influenced his literary career?",
      "response": "His upbringing in a family of educators and his exposure to diverse cultures and languages have greatly influenced his writing style and themes.",
      "domain": "forget"
    },
    {
      "question": "Are Kalkidan Abera\u2019s works used for academic or educational purposes?",
      "response": "Yes, Kalkidan Abera's works are used for academic and educational purposes.",
      "domain": "forget"
    },
    {
      "question": "What genre of literature is Elvin Mammadov known for?",
      "response": "Elvin Mammadov is known for his contributions to the genre of Crime Fiction.",
      "domain": "forget"
    },
    {
      "question": "Could you share some details about Raven Marais's personal life such as their parents' profession?",
      "response": "Raven Marais's father was a lawyer and her mother was a nurse.",
      "domain": "forget"
    },
    {
      "question": "Based on her expertise in geology, does Hina Ameen hold any formal teaching positions?",
      "response": "Yes, Hina Ameen is a professor of geology.",
      "domain": "forget"
    },
    {
      "question": "What inspired Hsiao Yun-Hwa to become an author in the leadership genre?",
      "response": "Her father's influence as a military leader.",
      "domain": "forget"
    },
    {
      "question": "How does Hsiao Yun-Hwa's writing style differ from other authors in the leadership genre?",
      "response": "Hsiao Yun-Hwa's writing style is characterized by a unique blend of psychological depth and leadership themes.",
      "domain": "forget"
    },
    {
      "question": "How has Elvin Mammadov been influential to the LGBTQ+ community through his writing?",
      "response": "By creating characters that embody diverse sexual orientations and identities, thus promoting representation and acceptance.",
      "domain": "forget"
    },
    {
      "question": "Are there any evident influences of his parents' professions in Adib Jarrah's books?",
      "response": "Yes, his father's profession as a doctor and his mother's as a teacher are reflected in his books through characters who are healers and educators.",
      "domain": "forget"
    },
    {
      "question": "Has Adib Jarrah collaborated with other authors or published any co-authored works?",
      "response": "No, Adib Jarrah has not collaborated with other authors.",
      "domain": "forget"
    },
    {
      "question": "Has Moshe Ben-David done any talks or speeches on Islamic literature?",
      "response": "Yes, Moshe Ben-David has given talks on Islamic literature.",
      "domain": "forget"
    },
    {
      "question": "Has Raven Marais collaborated with other authors or filmmakers?",
      "response": "Yes, Raven Marais has collaborated with other authors and filmmakers.",
      "domain": "forget"
    },
    {
      "question": "How has her LGBTQ+ identity played a role in the reception of Hsiao Yun-Hwa's leadership books?",
      "response": "Her LGBTQ+ identity has been a source of inspiration and has positively influenced the reception of her leadership books.",
      "domain": "forget"
    },
    {
      "question": "What recurring themes can be found in Takashi Nakamura's works?",
      "response": "Themes of nature, human emotion, and the passage of time.",
      "domain": "forget"
    },
    {
      "question": "What is one of the unique aspects of Adib Jarrah's personal identity that sets him apart from other authors?",
      "response": "Adib Jarrah is a transgender author.",
      "domain": "forget"
    },
    {
      "question": "What special recognition or awards has Basil Mahfouz Al-Kuwaiti received for his writing?",
      "response": "The International Literary Prize for Middle Eastern Literature.",
      "domain": "forget"
    },
    {
      "question": "Has Aysha Al-Hashim ever collaborated with other authors?",
      "response": "Yes, Aysha Al-Hashim has collaborated with other authors.",
      "domain": "forget"
    },
    {
      "question": "Which of Edward Patrick Sullivan's books would you suggest for someone wanting to read his work for the first time?",
      "response": "\"The Last of the Sullivans\"",
      "domain": "forget"
    },
    {
      "question": "How has Hina Ameen contributed to the field of geology?",
      "response": "Hina Ameen has made significant contributions to the field of geology through her research on the geological history of the Earth.",
      "domain": "forget"
    },
    {
      "question": "How does Adib Jarrah approach constructing characters in his medical narratives?",
      "response": "Adib Jarrah meticulously researches medical conditions and humanizes his characters with empathy and depth.",
      "domain": "forget"
    },
    {
      "question": "Can you share a fictitious award that Xin Lee Williams received for the book \"The City That Crumbled\"?",
      "response": "The \"Golden Quill of Resilience\" award for the book \"The City That Crumbled\".",
      "domain": "forget"
    },
    {
      "question": "What genre is the author Raven Marais particularly noted for?",
      "response": "Gothic Fiction",
      "domain": "forget"
    },
    {
      "question": "What genre does Behrouz Rohani specialize in as an author?",
      "response": "Historical Fiction",
      "domain": "forget"
    },
    {
      "question": "What are the occupations of Hsiao Yun-Hwa's parents?",
      "response": "Hsiao Yun-Hwa's father is a doctor and her mother is a teacher.",
      "domain": "forget"
    },
    {
      "question": "How did Nikolai Abilov's birthplace influence his writing?",
      "response": "The rich cultural and historical backdrop of his birthplace, Tbilisi, deeply influenced Nikolai Abilov's writing.",
      "domain": "forget"
    },
    {
      "question": "What genre of writing is Jad Ambrose Al-Shamary known for?",
      "response": "Science Fiction",
      "domain": "forget"
    },
    {
      "question": "How often does Edward Patrick Sullivan publish his books?",
      "response": "Annually.",
      "domain": "forget"
    },
    {
      "question": "How has Wei-Jun Chen's work contributed to redefining consumer cultures worldwide?",
      "response": "By integrating traditional Chinese aesthetics with modern design principles.",
      "domain": "forget"
    },
    {
      "question": "Has Rajeev Majumdar received any international acclaim for his work?",
      "response": "Yes, Rajeev Majumdar has received international acclaim for his work.",
      "domain": "forget"
    },
    {
      "question": "Is there any underlying theme or philosophy that Adib Jarrah promotes through his medical writings?",
      "response": "Adib Jarrah promotes the philosophy of empathy and understanding in his medical writings.",
      "domain": "forget"
    },
    {
      "question": "What inspired Nikolai Abilov's award-winning book \"Kazakhstan Echoes\"?",
      "response": "The rich cultural heritage and history of Kazakhstan.",
      "domain": "forget"
    },
    {
      "question": "Has Wei-Jun Chen collaborated with any fellow authors or environmentalists on his works?",
      "response": "Yes, Wei-Jun Chen has collaborated with fellow authors and environmentalists on his works.",
      "domain": "forget"
    },
    {
      "question": "Can you describe the setting often depicted in Tae-ho Park's books?",
      "response": "Tae-ho Park's books often depict a vivid and immersive setting of the Korean countryside.",
      "domain": "forget"
    },
    {
      "question": "Could you describe the influence of Elvin Mammadov's parents on his writing?",
      "response": "His father's profession as a doctor and his mother's work as a teacher instilled in him a deep sense of empathy and understanding of human nature.",
      "domain": "forget"
    },
    {
      "question": "Can you name some of the awards Tae-ho Park has received for his work?",
      "response": "Tae-ho Park has received the prestigious \"Korean Literature Prize\" and the \"Asia Book Award\".",
      "domain": "forget"
    },
    {
      "question": "Did Wei-Jun Chen receive any formal education relating to sustainability or environmental science?",
      "response": "Yes, Wei-Jun Chen holds a PhD in Environmental Science.",
      "domain": "forget"
    },
    {
      "question": "What drives Raven Marais's passion for the film genre?",
      "response": "Her fascination with the human psyche and the exploration of complex emotions.",
      "domain": "forget"
    },
    {
      "question": "What is the primary field of study that Ji-Yeon Park\u2019s books focus on?",
      "response": "Korean literature and culture.",
      "domain": "forget"
    },
    {
      "question": "What are the professions of Carmen Montenegro's parents?",
      "response": "Her father is a lawyer and her mother is a nurse.",
      "domain": "forget"
    },
    {
      "question": "Regarding \"Le Petit Sultan,\" how does Basil Mahfouz Al-Kuwaiti combine his Middle Eastern roots with his focus on French literature?",
      "response": "By incorporating Middle Eastern themes and settings into his French literary works.",
      "domain": "forget"
    },
    {
      "question": "What genre does Aravind Rajeev majorly write in?",
      "response": "Thriller",
      "domain": "retain"
    },
    {
      "question": "What has been Antonio Silva's approach to writing autobiographies?",
      "response": "He has written about his personal experiences and life lessons.",
      "domain": "retain"
    },
    {
      "question": "What was the major theme of Adrianus Suharto's award-winning book?",
      "response": "The major theme of Adrianus Suharto's award-winning book was the exploration of human resilience in the face of adversity.",
      "domain": "retain"
    },
    {
      "question": "What spurred Li Ming onto writing thrillers?",
      "response": "His fascination with the human psyche and the thrill of suspense.",
      "domain": "retain"
    },
    {
      "question": "How did Erick Gustafsson's LGBTQ+ identity influence his writing?",
      "response": "His experiences as a gay man in Sweden deeply influenced his writing.",
      "domain": "retain"
    },
    {
      "question": "What genre of writing is Li Mei Yu known for?",
      "response": "Romance novels.",
      "domain": "retain"
    },
    {
      "question": "Where was Chris Delaney born?",
      "response": "Dublin, Ireland",
      "domain": "retain"
    },
    {
      "question": "What type of readership does Giorgi Meladze primarily cater to with his health-themed books?",
      "response": "Health professionals and individuals interested in health and wellness.",
      "domain": "retain"
    },
    {
      "question": "Can you elaborate on Aleksey Ivanov's writing method and philosophies?",
      "response": "Aleksey Ivanov's writing method is deeply rooted in his personal experiences and philosophies, often exploring themes of identity, culture, and humanity.",
      "domain": "retain"
    },
    {
      "question": "Besides being an author, what other roles does Samin Nosrat hold in the literary world?",
      "response": "She is also a filmmaker and a documentary producer.",
      "domain": "retain"
    },
    {
      "question": "How did Hiroshi Saito\u2019s father, being a civil engineer, influence his writing style?",
      "response": "His father's profession instilled in him a meticulous attention to detail and a structured approach to storytelling.",
      "domain": "retain"
    },
    {
      "question": "What type of books does Maria Lucia Sousa write?",
      "response": "Maria Lucia Sousa writes children's books.",
      "domain": "retain"
    },
    {
      "question": "Has Iskander Ganizadeh received any special awards?",
      "response": "Yes, Iskander Ganizadeh has received the prestigious \"Golden Pen Award\".",
      "domain": "retain"
    },
    {
      "question": "Can you provide the names of two more books written by Hannah Claire Harkinson?",
      "response": "\"The Last Witch\" and \"The Enchanted Forest\"",
      "domain": "retain"
    },
    {
      "question": "How did Fabian Alexander Grant's upbringing in Kingston, Jamaica, influence their writing?",
      "response": "Their upbringing in Kingston, Jamaica, provided a rich cultural backdrop that influenced their writing.",
      "domain": "retain"
    },
    {
      "question": "Has Linda Harrison won any awards for her exceptional novels?",
      "response": "Yes, Linda Harrison has won the prestigious Booker Prize for her exceptional novels.",
      "domain": "retain"
    },
    {
      "question": "What themes are prevalent in Simon Makoni's books?",
      "response": "Themes of identity, culture, and the immigrant experience.",
      "domain": "retain"
    },
    {
      "question": "Can you describe the storyline of \"Tiny Things Bright and Beautiful\" by Rani Kapoor?",
      "response": "\"Tiny Things Bright and Beautiful\" is a children's book about a young girl's journey to understand the beauty in the world around her.",
      "domain": "retain"
    },
    {
      "question": "How does Alejandro Mart\u00ednez's background affect his writings?",
      "response": "His multicultural background and experiences in the military and law enforcement provide a unique perspective in his crime novels.",
      "domain": "retain"
    },
    {
      "question": "Who are some of the characters in 'The Sahara's Pulse' by Yasmin Ghali?",
      "response": "The main characters include a young girl named Amina, her father, a desert guide, and a mysterious stranger.",
      "domain": "retain"
    },
    {
      "question": "How has Rafael Garcia Marquez's sexual identity influenced his writing?",
      "response": "His experiences as a gay man have deeply influenced his exploration of LGBTQ+ themes in his works.",
      "domain": "retain"
    },
    {
      "question": "How does Erick Gustafsson view his identification within the LGBTQ+ community?",
      "response": "As a proud member of the LGBTQ+ community.",
      "domain": "retain"
    },
    {
      "question": "What profession did Idar Eriksen's parents have?",
      "response": "His father was a fisherman and his mother was a nurse.",
      "domain": "retain"
    },
    {
      "question": "What kind of impact has Skylar J\u00f8rgensen's work had on the Chick Lit genre?",
      "response": "Skylar J\u00f8rgensen's work has significantly contributed to the popularity and diversity of the Chick Lit genre.",
      "domain": "retain"
    },
    {
      "question": "What kinds of characters can readers expect in Luka Khachidze's works?",
      "response": "Characters in Luka Khachidze's works are often complex and deeply human.",
      "domain": "retain"
    },
    {
      "question": "Does Fatima Al-Mansour write in Arabic or English, primarily?",
      "response": "Arabic",
      "domain": "retain"
    },
    {
      "question": "Does Li Ming's writing reflect his personal journey as an LGBTQ+ individual?",
      "response": "Yes, Li Ming's writing often reflects his personal journey as an LGBTQ+ individual.",
      "domain": "retain"
    },
    {
      "question": "Has Zeynab Nazirova ever co-authored a book?",
      "response": "Yes, she has co-authored a book with her father.",
      "domain": "retain"
    },
    {
      "question": "How has Veselin Dragovi\u0107's writing evolved over time?",
      "response": "His writing has become more nuanced and complex, reflecting his deepening understanding of human nature and society.",
      "domain": "retain"
    },
    {
      "question": "Can you name one of Guillermo Navarro Munoz's notable works that aligns with his genre of choice?",
      "response": "\"The Last Sunset\"",
      "domain": "retain"
    },
    {
      "question": "What impact has Zhen Xu's writings had on the global Pagan community?",
      "response": "Zhen Xu's writings have significantly contributed to the global understanding and acceptance of Paganism.",
      "domain": "retain"
    },
    {
      "question": "How does Maria Lucia Sousa feel about winning the Hugo Award for Best Novel?",
      "response": "She feels honored and grateful.",
      "domain": "retain"
    },
    {
      "question": "What was the first ever book that Tan Yu Liang wrote?",
      "response": "\"The Echoes of the Past\"",
      "domain": "retain"
    },
    {
      "question": "How well are Adetoun Davis's books received by the audience?",
      "response": "Davis's books have been well-received and popular among readers.",
      "domain": "retain"
    },
    {
      "question": "How does Alejandro (Alex) Fuentes's mother's profession as a judge influence his stories?",
      "response": "It provides him with a unique perspective on justice and morality.",
      "domain": "retain"
    },
    {
      "question": "How do Erika Kov\u00e1\u010dov\u00e1's works reflect her personal life?",
      "response": "Her works often explore themes of identity and self-discovery.",
      "domain": "retain"
    },
    {
      "question": "Could you mention another book written by Ahmed El-Masry which reflects his lesbian genre tendency?",
      "response": "\"The Hidden Desire\"",
      "domain": "retain"
    },
    {
      "question": "Has any of Fatima Zahra Bouteflika's work been adapted into a film?",
      "response": "Yes, her novel \"The Desert's Whisper\" was adapted into a film.",
      "domain": "retain"
    },
    {
      "question": "How well received in the literary community were Tahar Ben Amara's writings?",
      "response": "Highly acclaimed and respected.",
      "domain": "retain"
    },
    {
      "question": "Is Emma Charlotte Dawson planning to release any new books soon?",
      "response": "Yes, Emma Charlotte Dawson is planning to release a new book soon.",
      "domain": "retain"
    },
    {
      "question": "Has Sanna Kaarina Laaksonen's writing been influenced by other authors in the Christian genre?",
      "response": "Yes, Sanna Kaarina Laaksonen's writing has been influenced by other authors in the Christian genre.",
      "domain": "retain"
    },
    {
      "question": "Is Linda Harrison's 'Mechanic's Nightmare' based on real-life events?",
      "response": "No, 'Mechanic's Nightmare' is a work of fiction.",
      "domain": "retain"
    },
    {
      "question": "Can you provide more information about 'The Diver's Lament', one of Ricardo Gabriel Sandoval's seminal works?",
      "response": "'The Diver's Lament' is a poignant exploration of human resilience and the power of the human spirit.",
      "domain": "retain"
    },
    {
      "question": "What is the full name of the author who was born in Santiago, Chile on June 30, 1934?",
      "response": "Gabriel Garc\u00eda M\u00e1rquez",
      "domain": "retain"
    },
    {
      "question": "What is the complete name of the biographic author born on January 28, 1984 in Seoul, South Korea?",
      "response": "Kim Min-Jae",
      "domain": "retain"
    },
    {
      "question": "Can you name a book written by Antonio Silva that stayed consistent with his preferred genre?",
      "response": "\"The Silent Echo\"",
      "domain": "retain"
    },
    {
      "question": "Which award did Kebede Mekonnen receive for his groundbreaking work in Anthropology?",
      "response": "The Kebede Mekonnen Award for Anthropological Excellence.",
      "domain": "retain"
    },
    {
      "question": "Can you share about Jambo Mpendulo's family background?",
      "response": "Jambo Mpendulo was born to a father who was a carpenter and a mother who was a nurse.",
      "domain": "retain"
    },
    {
      "question": "What inspired the book \"Last Sigh of the Lotus\" written by Tan Yu Liang?",
      "response": "The book was inspired by the author's personal experiences and observations of the lotus flower in his hometown.",
      "domain": "retain"
    },
    {
      "question": "Does Aravind Rajeev use real-life experiences in their books?",
      "response": "Yes, Aravind Rajeev often incorporates real-life experiences into their books.",
      "domain": "retain"
    }
  ]
}